crypt_guard-0.1.0.dist-info/METADATA
crypt_guard-0.1.0.dist-info/WHEEL
crypt_guard/__init__.py
crypt_guard/crypt_guard.cpython-312-x86_64-linux-gnu.so
crypt_guard-0.1.0.dist-info/RECORD
