Metadata-Version: 2.3
Name: crypt_guard
Version: 0.1.0
Summary: CryptGuardLib is a comprehensive Rust library designed for strong encryption and decryption, incorporating post-quantum cryptography to safeguard against quantum threats. It's geared towards developers who need to embed advanced cryptographic capabilities in their Rust applications.
License: MIT
Project-URL: Source Code, https://github.com/mm9942/crypt_guard_py
